client_server/__init__.py
client_server/base_define.py
client_server/object.py
client_server/rpc.py
client_server/rq_sdk_request.py
client_server/rqsdk_engine.py
strategies/__init__.py
strategies/option_trading_strategy.py
vnpy/__init__.py
vnpy/chart/__init__.py
vnpy/chart/axis.py
vnpy/chart/base.py
vnpy/chart/item.py
vnpy/chart/manager.py
vnpy/chart/widget.py
vnpy/event/__init__.py
vnpy/event/engine.py
vnpy/rpc/__init__.py
vnpy/rpc/client.py
vnpy/rpc/common.py
vnpy/rpc/server.py
vnpy/trader/__init__.py
vnpy/trader/app.py
vnpy/trader/constant.py
vnpy/trader/converter.py
vnpy/trader/database.py
vnpy/trader/datafeed.py
vnpy/trader/engine.py
vnpy/trader/event.py
vnpy/trader/gateway.py
vnpy/trader/object.py
vnpy/trader/optimize.py
vnpy/trader/setting.py
vnpy/trader/utility.py
vnpy/trader/ui/__init__.py
vnpy/trader/ui/mainwindow.py
vnpy/trader/ui/qt.py
vnpy/trader/ui/widget.py
vnpy/trader/ui/ico/__init__.py
vnpy_clickhouse/__init__.py
vnpy_clickhouse/clickhouse_database.py
vnpy_ctabacktester/__init__.py
vnpy_ctabacktester/engine.py
vnpy_ctabacktester/ui/__init__.py
vnpy_ctabacktester/ui/widget.py
vnpy_ctastrategy/__init__.py
vnpy_ctastrategy/backtesting.py
vnpy_ctastrategy/base.py
vnpy_ctastrategy/engine.py
vnpy_ctastrategy/symbols_operator.py
vnpy_ctastrategy/template.py
vnpy_ctastrategy/strategies/__init__.py
vnpy_ctastrategy/strategies/atr_rsi_strategy.py
vnpy_ctastrategy/strategies/boll_channel_strategy.py
vnpy_ctastrategy/strategies/boll_channel_strategy_leo.py
vnpy_ctastrategy/strategies/double_ma_strategy.py
vnpy_ctastrategy/strategies/dual_thrust_strategy.py
vnpy_ctastrategy/strategies/king_keltner_strategy.py
vnpy_ctastrategy/strategies/multi_signal_strategy.py
vnpy_ctastrategy/strategies/multi_timeframe_strategy.py
vnpy_ctastrategy/strategies/test_strategy.py
vnpy_ctastrategy/strategies/turtle_signal_strategy.py
vnpy_ctastrategy/ui/__init__.py
vnpy_ctastrategy/ui/rollover.py
vnpy_ctastrategy/ui/widget.py
vnpy_ctp/__init__.py
vnpy_ctp/api/__init__.py
leo_vnpy_ctp-1.0.4.dist-info/LICENSE
leo_vnpy_ctp-1.0.4.dist-info/METADATA
leo_vnpy_ctp-1.0.4.dist-info/WHEEL
leo_vnpy_ctp-1.0.4.dist-info/top_level.txt
leo_vnpy_ctp-1.0.4.dist-info/RECORD
