Metadata-Version: 2.1
Name: leo-vnpy-ctp
Version: 1.0.4
Summary: CTP gateway for vn.py quant trading framework.
Home-page: https://www.vnpy.com
Author: Xiaoyou Chen
Author-email: xiaoyou.chen@mail.vnpy.com
License: MIT
Keywords: quant,quantitative,investment,trading,algotrading,ctp
Classifier: Development Status :: 5 - Production/Stable
Classifier: Operating System :: Microsoft :: Windows
Classifier: Operating System :: POSIX :: Linux
Classifier: Programming Language :: Python :: 3
Classifier: Programming Language :: Python :: 3.7
Classifier: Programming Language :: Python :: 3.8
Classifier: Programming Language :: Python :: 3.9
Classifier: Programming Language :: Python :: 3.10
Classifier: Topic :: Office/Business :: Financial :: Investment
Classifier: Programming Language :: Python :: Implementation :: CPython
Classifier: License :: OSI Approved :: MIT License
Classifier: Natural Language :: Chinese (Simplified)
Requires-Python: >=3.7
License-File: LICENSE
Requires-Dist: importlib-metadata
Requires-Dist: pandas (==1.5.3)
Requires-Dist: deap (==1.3.3)
Requires-Dist: plotly (==5.13.1)
Requires-Dist: rqdatac (==2.10.14.2)
Requires-Dist: openpyxl (==3.1.2)
Requires-Dist: zmq (==0.0.0)
Requires-Dist: tzlocal (==4.3)
Requires-Dist: pymongo (==4.3.3)
